{"trial_id": "06", "hyperparameters": {"space": [{"class_name": "Int", "config": {"name": "units", "default": null, "conditions": [], "min_value": 16, "max_value": 128, "step": 16, "sampling": "linear"}}, {"class_name": "Choice", "config": {"name": "learning_rate", "default": 0.01, "conditions": [], "values": [0.01, 0.001, 0.0001], "ordered": true}}, {"class_name": "Boolean", "config": {"name": "bidirectional", "default": true, "conditions": []}}, {"class_name": "Float", "config": {"name": "dropout", "default": 0.2, "conditions": [], "min_value": 0.0, "max_value": 0.5, "step": 0.1, "sampling": "linear"}}], "values": {"units": 16, "learning_rate": 0.001, "bidirectional": false, "dropout": 0.0}}, "metrics": {"metrics": {"first_five_accuracy": {"direction": "min", "observations": [{"value": [0.08006329089403152], "step": 18}]}, "first_five_loss": {"direction": "min", "observations": [{"value": [3.5873656272888184], "step": 18}]}, "loss": {"direction": "min", "observations": [{"value": [6.700045585632324], "step": 18}]}, "sixth_accuracy": {"direction": "min", "observations": [{"value": [0.07594936341047287], "step": 18}]}, "sixth_loss": {"direction": "min", "observations": [{"value": [3.113527774810791], "step": 18}]}, "val_first_five_accuracy": {"direction": "min", "observations": [{"value": [0.040506333112716675], "step": 18}]}, "val_first_five_loss": {"direction": "min", "observations": [{"value": [3.8113784790039062], "step": 18}]}, "val_loss": {"direction": "min", "observations": [{"value": [7.278556823730469], "step": 18}]}, "val_sixth_accuracy": {"direction": "min", "observations": [{"value": [0.025316456332802773], "step": 18}]}, "val_sixth_loss": {"direction": "min", "observations": [{"value": [3.464763641357422], "step": 18}]}}}, "score": 7.278556823730469, "best_step": 18, "status": "COMPLETED", "message": null}